autoapi/__init__.py
autoapi/_astroid_utils.py
autoapi/_mapper.py
autoapi/_objects.py
autoapi/_parser.py
autoapi/directives.py
autoapi/documenters.py
autoapi/extension.py
autoapi/inheritance_diagrams.py
autoapi/settings.py
autoapi/templates/index.rst
autoapi/templates/python/attribute.rst
autoapi/templates/python/class.rst
autoapi/templates/python/data.rst
autoapi/templates/python/exception.rst
autoapi/templates/python/function.rst
autoapi/templates/python/method.rst
autoapi/templates/python/module.rst
autoapi/templates/python/package.rst
autoapi/templates/python/property.rst
sphinx_autoapi-3.4.0.dist-info/WHEEL
sphinx_autoapi-3.4.0.dist-info/METADATA
sphinx_autoapi-3.4.0.dist-info/RECORD
