Metadata-Version: 2.3
Name: sphinx-autoapi
Version: 3.4.0
Summary: Sphinx API documentation generator
Author-email: Eric Holscher <eric@ericholscher.com>
Maintainer-email: Ashley Whetter <ashley@awhetter.co.uk>
Requires-Python: >=3.8
Classifier: Development Status :: 5 - Production/Stable
Classifier: Environment :: Plugins
Classifier: Framework :: Sphinx :: Extension
Classifier: Intended Audience :: Developers
Classifier: License :: OSI Approved :: MIT License
Classifier: Natural Language :: English
Classifier: Programming Language :: Python
Classifier: Programming Language :: Python :: 3
Classifier: Programming Language :: Python :: 3.8
Classifier: Programming Language :: Python :: 3.9
Classifier: Programming Language :: Python :: 3.10
Classifier: Programming Language :: Python :: 3.11
Classifier: Programming Language :: Python :: 3.12
Classifier: Programming Language :: Python :: 3.13
Requires-Dist: astroid>=2.7;python_version<"3.12"
Requires-Dist: astroid>=3.0.0a1;python_version>="3.12"
Requires-Dist: Jinja2
Requires-Dist: PyYAML
Requires-Dist: sphinx>=6.1.0
Requires-Dist: stdlib_list;python_version<"3.10"
Project-URL: Documentation, https://sphinx-autoapi.readthedocs.io/en/latest/
Project-URL: Homepage, http://github.com/readthedocs/sphinx-autoapi
